django_request_trace
